setup.cfg
setup.py
email_parser/__init__.py
email_parser/clients.py
email_parser/cmd.py
email_parser/errors.py
email_parser/fs.py
email_parser/link_shortener.py
email_parser/markdown_ext.py
email_parser/placeholder.py
email_parser/reader.py
email_parser/renderer.py
email_parser/utils.py
email_parser/gui/__init__.py
email_parser/gui/gui.py
email_parser/gui/service.py
email_parser/resources/__init__.py
email_parser/resources/gui/__init__.py
ks_email_parser.egg-info/PKG-INFO
ks_email_parser.egg-info/SOURCES.txt
ks_email_parser.egg-info/dependency_links.txt
ks_email_parser.egg-info/entry_points.txt
ks_email_parser.egg-info/requires.txt
ks_email_parser.egg-info/top_level.txt