Metadata-Version: 1.1
Name: ks-email-parser
Version: 0.2.7
Summary: A command line tool to render HTML and text emails of markdown content.
Home-page: https://github.com/KeepSafe/ks-email-parser
Author: Keepsafe
Author-email: support@getkeepsafe.com
License: Apache
Platform: UNKNOWN
Classifier: License :: OSI Approved :: BSD License
Classifier: Intended Audience :: Developers
Classifier: Programming Language :: Python
